SmartCVParserAPI/__init__.py
SmartCVParserAPI/app6.py
SmartCVParserAPI/static/styles.css
SmartCVParserAPI/templates/index.html
SmartCVParserAPI/templates/interact.html
SmartCVParserAPI-0.1.0.dist-info/METADATA
SmartCVParserAPI-0.1.0.dist-info/WHEEL
SmartCVParserAPI-0.1.0.dist-info/entry_points.txt
SmartCVParserAPI-0.1.0.dist-info/top_level.txt
SmartCVParserAPI-0.1.0.dist-info/RECORD
